<?xml version="1.0" encoding="utf-8"?>
<content>
    <label>
        <key>sort_by_name</key>
        <value>Sort by Namn</value>
    </label>
    <label>
        <key>sort_by_role</key>
        <value>Sort by Roll</value>
    </label>
    <label>
        <key>sort_by_error_login</key>
        <value>Sort by Login fel</value>
    </label>
    <label>
        <key>sort_by_login</key>
        <value>Sort by Inloggade</value>
    </label>
    <label>
        <key>active_employees</key>
        <value>Aktiva anställda</value>
    </label>
    <label>
        <key>inactive_employees</key>
        <value>Raderade/dolda anställda</value>
    </label>
    <label>
        <key>assign_customer</key>
        <value>Tilldela Kund</value>
    </label>
    <label>
        <key>remove_customer</key>
        <value>Ta bort Kund</value>
    </label>
    <label>
        <key>assign_employee</key>
        <value>Koppla assistent till kund</value>
    </label>
    <label>
        <key>remove_employee</key>
        <value>Koppla bort assistent från kund</value>
    </label>
    <label>
        <key>remove_employee_tooltip</key>
        <value>Ta bort meddelande</value>
    </label>
    <label>
        <key>tltp_goto_week</key>
        <value>Gå till vecka:</value>
    </label>
    <label>
        <key>tltp_mini_maxi_week</key>
        <value>Minimera/Maximera</value>
    </label>
    <label>
        <key>tltp_goto_next_month</key>
        <value>Till nästa månad</value>
    </label>
    <label>
        <key>tltp_goto_previous_month</key>
        <value>Till föregåede månad</value>
    </label>
    <label>
        <key>tltp_goto_next_year</key>
        <value>Till nästa år</value>
    </label>
    <label>
        <key>tltp_goto_previous_year</key>
        <value>Till föregående år</value>
    </label>
    <label>
        <key>tltp_goto_todays_month</key>
        <value>Gå till nuvarande månad</value>
    </label>
    <label>
        <key>tltp_select_year_month</key>
        <value>Välj år/månad</value>
    </label>
    <label>
        <key>go_to_slots</key>
        <value>Gå till arbetspass</value>
    </label>
    <label>
        <key>tltp_go_to_monthly_view</key>
        <value>Gå till månadsvy</value>
    </label>
    <label>
        <key>tltp_go_to_customer_employee_week_page</key>
        <value>Gå till kund/assistent veckoschema</value>
    </label>
    <label>
        <key>tooltip_leave_in_advance_employee</key>
        <value>Semster i förskott</value>
    </label>
    <label>
        <key>tooltip_leave_in_advance_company</key>
        <value>Semster i förskott</value>
    </label>
    <label>
        <key>tooltip_exceeded_contract_hours</key>
        <value>Exceeded contract hours</value>
    </label>
    <label>
        <key>tooltip_incompleted_contract_hours</key>
        <value>Incomplete contract hours</value>
    </label>
    <label>
        <key>tooltip_new_slot</key>
        <value>Add new slot</value>
    </label>
    <label>
        <key>tooltip_substitute</key>
        <value>Substitute Employee</value>
    </label>
    <label>
        <key>company_edit_save_alert_message</key>
        <value>if changes are done contact person of the company will get notified do you want to continue YES/NO</value>
    </label>
    <label>
        <key>add_new_category</key>
        <value>Add New Category</value>
    </label>
     <label>
        <key>path</key>
        <value>Path : </value>
    </label>
    <label>
        <key>root</key>
        <value>Root</value>
    </label>
    <label>
        <key>select_parent</key>
        <value>Select Parent</value>
    </label>
    <label>
        <key>skill_title</key>
        <value>title</value>
    </label>
    <label>
        <key>skill_description</key>
        <value>Description</value>
    </label>
    <label>
        <key>skill_date_of_exam</key>
        <value>Exam date</value>
    </label>
</content>
